smart_segment/__init__.py
smart_segment/optimization.py
smart_segment/segmentation.py
smart_segment/utils.py
tests/__init__.py
tests/test_optimization.py
tests/test_segmentation.py
tests/test_utils.py
smart_segment-0.1.7.dist-info/LICENSE
smart_segment-0.1.7.dist-info/METADATA
smart_segment-0.1.7.dist-info/WHEEL
smart_segment-0.1.7.dist-info/top_level.txt
smart_segment-0.1.7.dist-info/RECORD
